assignment2/alucontrol.vhd
library ieee;
use ieee.std_logic_1164.all;

entity ALUControl is
-- Functionality should match truth table shown in Figure 4.13 in the textbook.
-- Check table on page2 of ISA.pdf on canvas. Pay attention to opcode of operations and type of operations. 
-- If an operation doesn't use ALU, you don't need to check for its case in the ALU control implemenetation.	
--  To ensure proper functionality, you must implement the "don't-care" values in the funct field,
-- for example when ALUOp = '00", Operation must be "0010" regardless of what Funct is.
port(
     ALUOp     : in  STD_LOGIC_VECTOR(1 downto 0);
     Opcode    : in  STD_LOGIC_VECTOR(10 downto 0);
     Operation : out STD_LOGIC_VECTOR(3 downto 0)
    );
end ALUControl;

architecture rtl of ALUControl is
begin
    process(ALUOp, Opcode)
    begin
        if ALUOp(1 downto 0)="00" then
            operation <= "0010";
        elsif ALUOp(0)='1' then
            operation <= "0111";
        elsif ALUOp(1) = '1' then
            if Opcode(10 downto 0) = "10001011000" then
                operation <= "0010";
            elsif Opcode(10 downto 0) = "11001011000" or Opcode(10 downto 1) = "1101000100" then -- sub/sub
                operation <= "0110";
            elsif Opcode(10 downto 0) = "10001010000" then
                operation <= "0000";
            elsif Opcode(10 downto 0) = "10101010000" then
                operation <= "0001";
            end if;
        else
            operation <= "0000";
        end if;
    end process;
    
end rtl;

assignment4/tb/alucontrol_tb.vhd
library ieee;
use ieee.std_logic_1164.all;

entity alucontrol_tb is
end alucontrol_tb;

architecture behave of alucontrol_tb is
    component ALUCONTROL
    port(
        ALUOp     : in  STD_LOGIC_VECTOR(1 downto 0);
        Opcode    : in  STD_LOGIC_VECTOR(10 downto 0);
        Operation : out STD_LOGIC_VECTOR(3 downto 0)
    );
    end component;

    -- Add signals
    signal in_sig0 : std_logic_vector(1 downto 0) := "00";
    signal in_sig1 : std_logic_vector(10 downto 0) := "11111111111";
    signal output_sig : std_logic_vector(3 downto 0);

begin
    alucontrol_inst: ALUCONTROL
    -- Update Port map
    port map(
        ALUOp => in_sig0,
        OpCode => in_sig1,
        Operation => output_sig
    );

    process is
    begin

        in_sig0 <= "00";
        wait for 20 ns;

        in_sig0 <= "01";
        wait for 20 ns;

        in_sig0 <= "10";
        in_sig1 <= "10001011000";
        wait for 20 ns;

        in_sig0 <= "01";
        wait for 20 ns;
        
        in_sig0 <= "10";
        in_sig1 <= "11001011000";
        wait for 20 ns;

        in_sig0 <= "01";
        wait for 20 ns;
        
        in_sig0 <= "10";
        in_sig1 <= "10001010000";
        wait for 20 ns;

        in_sig0 <= "01";
        wait for 20 ns;
        
        in_sig0 <= "10";
        in_sig1 <= "10101010000";
        wait for 20 ns;

        in_sig0 <= "01";
        wait for 20 ns;
        
        wait;
    end process;

end behave;
-- end architecture;

-- vcom -quiet -2008 alucontrol.vhd alucontrol_tb.vhd
-- vsim -quiet -c work.alucontrol_tb -do "log -r /*; run 500ns; exit" -wlf alucontrol.wlf
-- wlf2vcd alucontrol.wlf -o alucontrol.vcd

assignment2/alucontrol.vcd
$date
	Wed Oct  6 13:14:02 2021
$end
$version
	QuestaSim Version 10.7c
$end
$timescale
	1ns
$end
$scope module alucontrol_tb $end
$var wire 1 ! in_sig0 [1] $end
$var wire 1 " in_sig0 [0] $end
$var wire 1 # in_sig1 [10] $end
$var wire 1 $ in_sig1 [9] $end
$var wire 1 % in_sig1 [8] $end
$var wire 1 & in_sig1 [7] $end
$var wire 1 ' in_sig1 [6] $end
$var wire 1 ( in_sig1 [5] $end
$var wire 1 ) in_sig1 [4] $end
$var wire 1 * in_sig1 [3] $end
$var wire 1 + in_sig1 [2] $end
$var wire 1 , in_sig1 [1] $end
$var wire 1 - in_sig1 [0] $end
$var wire 1 . output_sig [3] $end
$var wire 1 / output_sig [2] $end
$var wire 1 0 output_sig [1] $end
$var wire 1 1 output_sig [0] $end
$scope module alucontrol_inst $end
$var wire 1 2 ALUOp [1] $end
$var wire 1 3 ALUOp [0] $end
$var wire 1 4 Opcode [10] $end
$var wire 1 5 Opcode [9] $end
$var wire 1 6 Opcode [8] $end
$var wire 1 7 Opcode [7] $end
$var wire 1 8 Opcode [6] $end
$var wire 1 9 Opcode [5] $end
$var wire 1 : Opcode [4] $end
$var wire 1 ; Opcode [3] $end
$var wire 1 < Opcode [2] $end
$var wire 1 = Opcode [1] $end
$var wire 1 > Opcode [0] $end
$var wire 1 ? Operation [3] $end
$var wire 1 @ Operation [2] $end
$var wire 1 A Operation [1] $end
$var wire 1 B Operation [0] $end
$upscope $end
$upscope $end
$enddefinitions $end
#0
0!
02
0"
03
1#
14
1$
15
1%
16
1&
17
1'
18
1(
19
1)
1:
1*
1;
1+
1<
1,
1=
1-
1>
0.
0?
0/
0@
10
1A
01
0B
0.
0?
0/
0@
10
1A
01
0B
#20
1"
13
1/
1@
11
1B
#40
0$
05
0%
06
0&
07
0(
09
0+
0<
0,
0=
0-
0>
1!
12
0"
03
0/
0@
01
0B
#60
0!
02
1"
13
1/
1@
11
1B
#80
1$
15
1!
12
0"
03
01
0B
#100
0!
02
1"
13
11
1B
#120
0$
05
0*
0;
1!
12
0"
03
0/
0@
00
0A
01
0B
#140
0!
02
1"
13
1/
1@
10
1A
11
1B
#160
1%
16
1!
12
0"
03
0/
0@
00
0A
#180
0!
02
1"
13
1/
1@
10
1A
